{
  "login_welcome_text": "Добро пожаловать в Экосистему будущего",
  "login_welcome_text_description": "Введите имя пользователя и пароль для входа в систему",
  "login_auth_text": "Авторизоваться",
  "login_auth_text_description": "Войдите, чтобы получить доступ к своей учетной записи.",
  "login_username": "Логин",
  "login_password": "Пароль",
  "login_register": "Войти",
  "language_uz": "Узбекский",
  "language_ru": "Русский",
  "language_en": "Английский",
  "alert_true_auth": "Вы успешно вошли в",
  "login_error": "Неверный номер телефона или пароль",
  "welcomeBusinessProfile" : "Добро пожаловать в \nЗАДАЧ MANAGER",
  "toStarted" : "Чтобы начать работу пройдите авторизацию",
  "loginToProfile" : "Вход в профиль",
  "loginToContinue" : "Войдите чтобы продолжить",
  "login" : "Логин",
  "enterPassword" : "Введите пароль",
  "offerpage_search": "Поиск",
  "offerpage_in_stock": "В наличии",
  "offerpage_expiration_date": "Срок",
  "offerpage_manufacturer": "Производитель",
  "offerpage_offer_place": "Месторасположение",
  "offerpage_duration": "Длительность",
  "offerpage_offer_cart": "Продукция",

  "offer_category": "Продукция",
  "offer_detail": "Описание продукта",
  "offer_detail_params": "Параметры",
  "offer_detail_quantity": "О задаче",
  "offer_detail_manufacturer": "Производитель",
  "offer_detail_description": "Описание",
  "offer_description_specialist": "Специалист",

  "specialist_category": "Выбрать",
  "specialist_time": "Время встречи",
  "specialist_time_type_by_time": "По времени",
  "specialist_live_queue": "Живая очередь",

  "errors_no_internet_title": "Нет соеденения с интернетом",
  "errors_no_internet_description": "Перезагрузите позже",
  "errors_no_internet_button": "Перезагрузить",
  "errors_no_have_offer_title": "Продукции нет",
  "errors_no_have_offer_description": "Обратитесь руководству",
  "errors_no_have_offer_button": "Перезагрузить",

  "profile_start_work": "Начата работа",
  "profile_language": "Язык",
  "profile_currency": "Валюта",
  "profile_exit": "Выход",
  "percentage": "Процент",

  "adduser_search": "Поиск",
  "adduser_user_info": "Зарегистрироваться",
  "adduser_phone": "Введите телефон клиента",
  "adduser_phone_button": "Создать",
  "adduser_add_to_cashier": "Добавить ко мне",
  "adduser_firstname": "Имя",
  "adduser_lastname": "Фамилия",
  "adduser_thirdname": "Отчетсво",
  "adduser_date_birth": "Дата рождения",
  "adduser_gender": "Пол",
  "adduser_gender_man": "Мужчина",
  "adduser_gender_woman": "Женщина",
  "adduser_profession": "Профессия",
  "adduser_profession_title": "Выберите профессию",
  "adduser_profession_search": "Поиск профессии",
  "adduser_profession_search_cancel": "Отмена",
  "adduser_region": "Регион",
  "adduser_region_title": "Выберите регион",
  "adduser_region_search": "Поиск региона",
  "adduser_region_search_cancel": "Отмена",
  "adduser_error_code_text_cant_empty": "Поле не может быть пустым",
  "adduser_coupon": "Купон",
  "adduser_coupon_title": "Выберите купон",
  "adduser_coupon_search": "Поиск купона",
  "adduser_add_family": "Добавить семью",
  "adduser_move_to_order": "В заказ",
  "adduser_save": "Сохранить",
  "adduser_pvc_add_offer": "Оформить услугу",
  "adduser_pvc_add_offer_phone": "Введите PVC для этого номера",
  "adduser_pvc_add_offer_button": "Введите PVC",

  "adduser_check_print_name": "Имя Фамилия",
  "adduser_check_print_date_birth": "Дата рождения",
  "adduser_check_print_region": "Регион",

  "adduser_history": "История",
  "adduser_history_last_visit": "Последнее посещение",
  "adduser_history_offer_status": "Статус заказов",
  "adduser_history_close_button": "Закрыть",
  "adduser_history_filter": "Фильтр",

  "special_title": "Специальные_параметры",
  "special_persent_for_offer": "Дисконт либо надбавка",
  "special_income_offer": "Приход товара",
  "special_time": "Время встречи",
  "special_time_type_by_time": "По времени",
  "special_live_queue": "Живая очередь",
  "special_meet_date": "Выберите дату встречи",
  "special_meet_time": "Выберите время встречи",
  "special_meet_time_busy": "Это время занято",
  "special_meet_time_not_work": "Специалист в этот день не работает",
  "special_monday": "Понедельник",
  "special_tuesday": "Вторник",
  "special_wednesday": "Среда",
  "special_thursday": "Четверг",
  "special_friday": "Пятница",
  "special_saturday": "Суббота",
  "special_sunday": "Воскресенье",
  "special_january": "Январь",
  "special_february": "Февраль",
  "special_march": "Маршировать",
  "special_april": "Апрель",
  "special_may": "Может",
  "special_june": "Июнь",
  "special_july": "Июль",
  "special_august": "Август",
  "special_september": "Сентябрь",
  "special_october": "Октябрь",
  "special_november": "Ноябрь",
  "special_december": "Декабрь",

  "cart_total_price_title": "Итоговая цена",
  "cart_price": "Цена",
  "cart_price_vat": "НДС",
  "cart_price_total": "Общий",
  "cart_order_cancel_button": "Отмена",
  "cart_order_to_order_button": "В заказ",
  "cart_order_to_pay_button": "Оплатить",
  "cart_coupon_title": "Оплатить",
  "cart_coupon_without_coupon": "Без купона",
  "cart_coupon_with_coupon": "С купоном",
  "cart_offer_quantity_title": "О задаче",
  "cart_offer_quantity": "Выберите о задаче",

  "pay_order_name": "Название заказа",
  "pay_order_cash": "Наличные",
  "pay_order_uzcard": "Узкард",
  "pay_order_humo": "Хумо",
  "pay_order_payment_button": "Оплата",
  "pay_order_prepaid_expense": "Аванс",
  "pay_order_anor": "Анор",
  "pay_discount": "Скидка",
  "pay_order_cashback": "Оплата по кешбеку",
  "pay_order_transfer": "Перевод на карту",
  "pay_total_price_title": "Итоговая цена",
  "pay_total_price_price": "Цена",
  "pay_total_price_vat": "НДС",
  "pay_total_price_total": "Общий",
  "pay_total_price_coupon": "Купон",
  "pay_total_price_deposited_money": "Внесено",
  "pay_total_price_short_change": "Сдача",
  "pay_type_offer_onplace": "На месте",
  "pay_type_offer_delivery": "Доставка",
  "pay_button_pay": "Оплатить",

  "order_who_create_order": "Касса",
  "order_position_inside_offer": "Vazifa haqida продукции",
  "order_client": "Клиент",
  "order_type": "Тип",
  "order_type_onplace": "На месте",
  "order_type_delivery": "доставка",
  "order_add_offer": "Добавить продукцию",
  "order_close": "Закрыть",
  "order_calendar": "Выберите дату",
  "order_filter": "Фильтр",
  "order_status_finished": "Завершенные",
  "order_status_canceled": "Отмененные",
  "order_status_open": "Открытые",
  "order_status_prepaid_expense": "Авансовые",

  "status_order_date_time": "Дата и время",
  "status_order_status": "Статус заказа",
  "status_order_type": "Тип",
  "status_order_quantity": "О задаче",
  "status_order_offer": "Продукция",
  "status_order_status_action": "Статус",
  "status_order_offer_name": "Название заказа",
  "status_order_client": "Клиент",
  "status_order_prepaid_expense": "Аванс",
  "status_order_total_cost": "Общая стоимость",
  "status_order_created_date": "Дата создания",
  "status_order_finished_date": "Дата Завершения",
  "status_order_time_spend": "Потраченное время",
  "status_order_offer_onplace": "На месте",
  "status_order_offer_delivery": "Доставка",

  "status_history_title": "История статусов",
  "status_history_time_spend": "Потраченное время",
  "status_history_time_spend_hour": "Час",
  "status_history_time_spend_minute": "Минут",

  "check_date": "Дата",
  "check_time": "Время",
  "check_check_number_count": "Номер чека",
  "check_cashier": "Кассир",
  "check_offer_title": "Заказ",
  "check_specialist": "Специалист",
  "check_profession": "Профессия",
  "check_without_vat": "Без НДС",
  "check_price": "Цена",
  "check_coupon": "Купон",
  "check_total_price": "Итоговая цена",
  "check_payment_button": "Оплата",
  "check_prepaid_expense": "Аванс",
  "check_transfer": "Перевод",
  "check_check_number": "Номер чека",
  "check_terminal_id": "ИД терминала",
  "check_fixal_sign": "Фискальный знак",
  "check_your_number": "Номер/время очереди",
  "check_qrcode_info": "Вы получили право на кэшбэк в размере 1% от покупки",
  "check_without_vat_by_coupon": "Купон",
  "check_if_offer_as_service": "Покажите QR-код врачу. Действителен в течение 30 дней",
  "check_cancel": "Отменен",
  "user_not_found": "Пользователь не найден",
  "forgot_your_password": "Забыли пароль?",
  "tasker": "Таскер",
  "task": "Задача",
  "age": "Возраст",
  "nothing_have": "Ничего не имеет",
  "history": "История",
  "scan_a_code": "Сканировать код",
  "bar_code_scanner": "Сканер штрих-кода",
  "loading": "Загрузка",
  "phone_or_jshir": "Телефон или JSHIR*",
  "jshshir": "Введите номер телефона с + или паспорт ЖШШИР без +",
  "create_account": "Зарегистрироваться",
  "select_a_task": "Выберите задачу",
  "there_is_no_task": "Нет задачи",
  "add_a_task": "Добавить задачу",
  "check_list": "Контрольный список",
  "comment": "Комментарий",
  "deposited_money": "Внесенные деньги",
  "payment_type": "Способ оплаты",
  "add_other_method_for_pay": "Добавить другой способ оплаты",
  "other_method": "Другой метод",
  "about_the_task": "О задаче",
  "assignment": "Назначение",
  "add_a_comment": "Добавить комментарий",
  "description_of_the_task": "Описание задачи",
  "payment": "К оплате",
  "premium": "Скидка/Премиум",
  "number_has_user": "У этого номера есть пользователь",
  "user_this_PINFL": "Есть пользователь с этим ПИНФЛ",
  "user_info": "Информация о пользователе",
  "user_history": "История пользователя",
  "user_retsept": "Рецепт пользователя",
  "soni": "Номер",
  "camera": "Камера",
  "card": "Корзинка",
  "retsept": "Рецепт",
  "my_rating": "Мой рейтинг",
  "scan": "Сканировать",
  "tasks": "Задания",
  "total": "Итого",
  "wholesale_trade": "Оптом торговля",
  "customers": "Клиенты",
  "map": "Карта",
  "all": "Все",
  "price_switchers": "Финансы",
  "select_your_profession": "Выберите свою профессию",
  "task_process": "Процесс задачи",
  "confirmation": "Подтверждение",
  "theme": "Режим",
  "general_information": "Общая информация",
  "offer_place": "Предложить место",
  "responsible_employees": "Ответственные сотрудники",
  "description": "Описание",
  "parameter": "Параметр",
  "expiry_date": "Дата истечения срока действия",
  "time_spent": "Время потрачено",
  "start_time": "Время начала",
  "organization": "Организация",
  "specialist": "Специалист",
  "show_more": "Показать больше",
  "hide": "Скрывать",
  "total_time_spent_task": "Общее время, потраченное на задачу",
  "responsible": "Ответственный",
  "you_change_status_orders": "Вы можете изменить статус заказов",
  "information_about_order": "Информация о заказе",
  "orders": "Заказы",
  "offline": "Не в сети",
  "waiting": "Ожидающий",
  "accepted": "Принял",
  "in_progress": "В ходе выполнения",
  "no_job_information": "Нет информации о вакансии",
  "closing_customer_account": "Закрытие учетной записи клиента",
  "paid": "Оплаченный",
  "working_time": "Рабочее время",
  "special_parameters": "Специальные параментры",
  "retail": "Розничная торговля",
  "printers": "Принтеры",
  "statistic": "Статистика",
  "accumulated_monthly_expenses": "Накопленные ежемесячные платежи и расходы",
  "product_category": "Категория товаров",
  "processing_data": "Обработка данных",
  "no_information_found": "Информация не найдена",
  "check_deposite_amount": "Сумма депозита",
  "language_uzb": "Узб",
  "language_rus": "Рус",
  "language_eng": "Анг",
  "kpi": "KPI",
  "sendSMS": "Отправить смс",
  "callAgainAfter": "Позвоните еще раз после",
  "timesCalled": "раз вызывали",
  "successful": "Успешный",
  "callTV": "Вызов клиента",
  "select_account": "Выберите учетную запись",
  "show_money": "Показать деньги",
  "profile": "Профиль",
  "profile_logout_yes": "Выйти",
  "log_out_profile": "Выйти из профиля",
  "cash_register": "Kассa",
  "sales": "Продажи",
  "number": "Номер",
  "monthly_payments": "Ежемесячные платежи",
  "expenses": "Затраты",
  "welcome": "Добро пожаловать в T-MED",
  "sign_up_electronic_queue": "Запишитесь на электронную очередь",
  "my_scores": "Мои результаты"
}
